quibble/__init__.py
quibble/nlp.py
quibble/casadi/__init__.py
quibble/casadi/_casadi.so
quibble/casadi/casadi.py
quibble/casadi/libcasadi.so
quibble/casadi/libcasadi_conic_cbc.so
quibble/casadi/libcasadi_conic_clp.so
quibble/casadi/libcasadi_conic_cplex.so
quibble/casadi/libcasadi_conic_gurobi.so
quibble/casadi/libcasadi_conic_nlpsol.so
quibble/casadi/libcasadi_conic_osqp.so
quibble/casadi/libcasadi_conic_qpoases.so
quibble/casadi/libcasadi_conic_qrqp.so
quibble/casadi/libcasadi_conic_superscs.so
quibble/casadi/libcasadi_dple_slicot.so
quibble/casadi/libcasadi_expm_slicot.so
quibble/casadi/libcasadi_importer_clang.so
quibble/casadi/libcasadi_importer_shell.so
quibble/casadi/libcasadi_integrator_collocation.so
quibble/casadi/libcasadi_integrator_cvodes.so
quibble/casadi/libcasadi_integrator_idas.so
quibble/casadi/libcasadi_integrator_rk.so
quibble/casadi/libcasadi_interpolant_bspline.so
quibble/casadi/libcasadi_interpolant_linear.so
quibble/casadi/libcasadi_linsol_csparse.so
quibble/casadi/libcasadi_linsol_csparsecholesky.so
quibble/casadi/libcasadi_linsol_lapacklu.so
quibble/casadi/libcasadi_linsol_lapackqr.so
quibble/casadi/libcasadi_linsol_ldl.so
quibble/casadi/libcasadi_linsol_lsqr.so
quibble/casadi/libcasadi_linsol_ma27.so
quibble/casadi/libcasadi_linsol_qr.so
quibble/casadi/libcasadi_linsol_symbolicqr.so
quibble/casadi/libcasadi_linsol_tridiag.so
quibble/casadi/libcasadi_nlpsol_ampl.so
quibble/casadi/libcasadi_nlpsol_blocksqp.so
quibble/casadi/libcasadi_nlpsol_bonmin.so
quibble/casadi/libcasadi_nlpsol_ipopt.so
quibble/casadi/libcasadi_nlpsol_knitro.so
quibble/casadi/libcasadi_nlpsol_qrsqp.so
quibble/casadi/libcasadi_nlpsol_scpgen.so
quibble/casadi/libcasadi_nlpsol_sqpmethod.so
quibble/casadi/libcasadi_nlpsol_worhp.so
quibble/casadi/libcasadi_rootfinder_fast_newton.so
quibble/casadi/libcasadi_rootfinder_kinsol.so
quibble/casadi/libcasadi_rootfinder_newton.so
quibble/casadi/libcasadi_rootfinder_nlpsol.so
quibble/casadi/libcasadi_sundials_common.so
quibble-0.0.1.dev1.dist-info/LICENSE
quibble-0.0.1.dev1.dist-info/METADATA
quibble-0.0.1.dev1.dist-info/WHEEL
quibble-0.0.1.dev1.dist-info/top_level.txt
quibble-0.0.1.dev1.dist-info/RECORD
