Metadata-Version: 2.1
Name: quibble
Version: 0.0.1.dev1
Summary: Framework for Various Optimization Tasks
Home-page: https://github.com/KarlSchwenk/quibble
Author: KarlSchwenk
Author-email: km.schwenk@web.de
License: LGPL-2.1
Platform: UNKNOWN
License-File: LICENSE
Requires-Dist: numpy (==1.18.5)
